LatvianStemmer.py
LatvianStemmer-1.0.2.dist-info/LICENSE
LatvianStemmer-1.0.2.dist-info/METADATA
LatvianStemmer-1.0.2.dist-info/WHEEL
LatvianStemmer-1.0.2.dist-info/entry_points.txt
LatvianStemmer-1.0.2.dist-info/top_level.txt
LatvianStemmer-1.0.2.dist-info/RECORD
