Metadata-Version: 2.1
Name: LatvianStemmer
Version: 1.0.2
Summary: Light stemmer for Latvian.
Home-page: https://github.com/rihardsk/LatvianStemmer
Author: Rihards Krišlauks
Author-email: rihizs@gmail.com
License: Apache License, Version 2.0
Platform: UNKNOWN
Classifier: Programming Language :: Python
Classifier: Programming Language :: Python :: 3
Classifier: License :: OSI Approved :: Apache Software License
Classifier: Operating System :: OS Independent
Classifier: Development Status :: 4 - Beta
Classifier: Intended Audience :: Developers
Classifier: Topic :: Text Processing :: Linguistic
Classifier: Topic :: Software Development :: Libraries :: Python Modules
